tensorframe/__init__.py
tensorframe/core/__init__.py
tensorframe/core/arrow.py
tensorframe/core/frame.py
tensorframe/core/parser.py
tensorframe/core/libs/__init__.py
tensorframe/core/libs/libbinops.so
tensorframe/core/libs/libio.so
tensorframe-0.80.6.dist-info/DESCRIPTION.rst
tensorframe-0.80.6.dist-info/METADATA
tensorframe-0.80.6.dist-info/RECORD
tensorframe-0.80.6.dist-info/WHEEL
tensorframe-0.80.6.dist-info/metadata.json
tensorframe-0.80.6.dist-info/top_level.txt
