Metadata-Version: 2.0
Name: tensorframe
Version: 0.80.6
Summary: Post alpha build
Home-page: https://tensorframe.ai
Author: Anthony Potappel
Author-email: anthony.potappel@gmail.com
License: UNKNOWN
Platform: UNKNOWN
Classifier: Operating System :: POSIX :: Linux
Classifier: License :: OSI Approved :: MIT License
Classifier: Programming Language :: Python :: 3.5
Classifier: Programming Language :: Python :: 3.6
Classifier: Programming Language :: Python :: 3.7
